zhuguang_sdk/__init__.py
zhuguang_sdk/core.py
zhuguang_sdk/thinterTheard.py
zhuguang_sdk/utils.py
zhuguang_sdk-1.0.8.dist-info/LICENSE
zhuguang_sdk-1.0.8.dist-info/METADATA
zhuguang_sdk-1.0.8.dist-info/WHEEL
zhuguang_sdk-1.0.8.dist-info/top_level.txt
zhuguang_sdk-1.0.8.dist-info/RECORD
